Metadata-Version: 2.1
Name: docker-with-criu
Version: 0.1.dev3304
Summary: A Python library for the Docker Engine API.
Home-page: https://github.com/docker/docker-py
Maintainer: Ulysses Souza
Maintainer-email: ulysses.souza@docker.com
License: Apache License 2.0
Project-URL: Documentation, https://docker-py.readthedocs.io
Project-URL: Changelog, https://docker-py.readthedocs.io/en/stable/change-log.html
Project-URL: Source, https://github.com/docker/docker-py
Project-URL: Tracker, https://github.com/docker/docker-py/issues
Classifier: Development Status :: 5 - Production/Stable
Classifier: Environment :: Other Environment
Classifier: Intended Audience :: Developers
Classifier: Operating System :: OS Independent
Classifier: Programming Language :: Python
Classifier: Programming Language :: Python :: 3
Classifier: Programming Language :: Python :: 3.7
Classifier: Programming Language :: Python :: 3.8
Classifier: Programming Language :: Python :: 3.9
Classifier: Programming Language :: Python :: 3.10
Classifier: Programming Language :: Python :: 3.11
Classifier: Topic :: Software Development
Classifier: Topic :: Utilities
Classifier: License :: OSI Approved :: Apache Software License
Requires-Python: >=3.7
License-File: LICENSE
Requires-Dist: packaging (>=14.0)
Requires-Dist: requests (>=2.26.0)
Requires-Dist: urllib3 (>=1.26.0)
Requires-Dist: websocket-client (>=0.32.0)
Requires-Dist: pywin32 (>=304) ; sys_platform == "win32"
Provides-Extra: ssh
Requires-Dist: paramiko (>=2.4.3) ; extra == 'ssh'
Provides-Extra: tls
